src/__init__.py
src/models.py
src/server.py
src/templates/base.html
src/templates/config_error.html
src/templates/error.html
src/templates/links.html
golinks-1.2.0.dist-info/METADATA
golinks-1.2.0.dist-info/WHEEL
golinks-1.2.0.dist-info/entry_points.txt
golinks-1.2.0.dist-info/licenses/LICENSE
golinks-1.2.0.dist-info/RECORD
