Metadata-Version: 2.4
Name: golinks
Version: 1.2.0
Summary: A local go links redirect service for URL shortcuts
Project-URL: Homepage, https://github.com/yourusername/golinks
Project-URL: Repository, https://github.com/yourusername/golinks.git
Project-URL: Issues, https://github.com/yourusername/golinks/issues
Author-email: Haran Rajkumar <haranrajkumar97@gmail.com>
License: MIT
License-File: LICENSE
Keywords: golinks,redirect,shortcuts,url-shortener
Classifier: Development Status :: 4 - Beta
Classifier: Intended Audience :: Developers
Classifier: License :: OSI Approved :: MIT License
Classifier: Operating System :: OS Independent
Classifier: Programming Language :: Python :: 3
Classifier: Programming Language :: Python :: 3.11
Classifier: Programming Language :: Python :: 3.12
Classifier: Topic :: Internet :: WWW/HTTP
Classifier: Topic :: Utilities
Requires-Python: >=3.11
Requires-Dist: jinja2>=3.1.6
Requires-Dist: pydantic>=2.11.9
